upyrc/__init__.py
upyrc/upyrc.py
upyrc/upyre.py
upyrc/re_templates/add_command_json_output_pipe.jinja
upyrc/re_templates/close_widget_bp_from_id.jinja
upyrc/re_templates/fbx_static_mesh_export.jinja
upyrc/re_templates/fbx_static_mesh_import.jinja
upyrc/re_templates/log.jinja
upyrc/re_templates/run_editor_bp_method.jinja
upyrc/re_templates/run_editor_widget_bp_method.jinja
upyrc/re_templates/spawn_utility_widget_bp.jinja
upyrc/upyre_json_pipe/__init__.py
upyrc/upyre_json_pipe/upyre_json_pipe.py
upyrc-0.12.0.dist-info/LICENSE
upyrc-0.12.0.dist-info/METADATA
upyrc-0.12.0.dist-info/WHEEL
upyrc-0.12.0.dist-info/top_level.txt
upyrc-0.12.0.dist-info/RECORD
