Metadata-Version: 2.1
Name: upyrc
Version: 0.12.0
Summary: Python wrapper around the Unreal engine remote control API and remote python execution.
Author-email: cgtoolbox <contact@cgtoolbox.com>
Project-URL: Homepage, https://github.com/cgtoolbox/UnrealRemoteControlWrapper
Requires-Python: >=3.7
License-File: LICENSE
Requires-Dist: requests
Requires-Dist: jinja2
